Metadata-Version: 2.4
Name: socaity-face2face
Version: 1.2.9
Summary: Swap faces from one image to another. Create face embeddings. Integrate into hosted environments.
Author: SocAIty
License: GPLv3
Project-URL: Repository, https://github.com/SocAIty/face2face
Project-URL: Homepage, https://www.socaity.ai
Requires-Python: >=3.8
License-File: LICENSE
Requires-Dist: tqdm
Requires-Dist: httpx
Requires-Dist: onnx>=1.19.0
Requires-Dist: onnxruntime-gpu>=1.23.0
Requires-Dist: media-toolkit>=00.02.18
Provides-Extra: full
Requires-Dist: fast-task-api>=1.2.8; extra == "full"
Dynamic: license-file
